serilog_python/__init__.py
serilog_python/config.py
serilog_python/filter.py
serilog_python/formatter.py
serilog_python-0.1.0.dist-info/LICENSE
serilog_python-0.1.0.dist-info/METADATA
serilog_python-0.1.0.dist-info/WHEEL
serilog_python-0.1.0.dist-info/top_level.txt
serilog_python-0.1.0.dist-info/RECORD
