Metadata-Version: 2.1
Name: serilog-python
Version: 0.1.0
Summary: Serilog-like JSON structured logging for Python applications
Author-email: Anton Irshenko <a_irshenko@example.com>
Maintainer-email: Anton Irshenko <a_irshenko@example.com>
License: MIT
Project-URL: Homepage, https://github.com/ton5169/serilog-python
Project-URL: Documentation, https://github.com/ton5169/serilog-python#readme
Project-URL: Repository, https://github.com/ton5169/serilog-python.git
Project-URL: Issues, https://github.com/ton5169/serilog-python/issues
Project-URL: Changelog, https://github.com/ton5169/serilog-python/blob/main/CHANGELOG.md
Keywords: logging,json,structured-logging,serilog,python
Classifier: Development Status :: 4 - Beta
Classifier: Intended Audience :: Developers
Classifier: License :: OSI Approved :: MIT License
Classifier: Operating System :: OS Independent
Classifier: Programming Language :: Python :: 3
Classifier: Programming Language :: Python :: 3.8
Classifier: Programming Language :: Python :: 3.9
Classifier: Programming Language :: Python :: 3.10
Classifier: Programming Language :: Python :: 3.11
Classifier: Programming Language :: Python :: 3.12
Classifier: Topic :: Software Development :: Libraries :: Python Modules
Classifier: Topic :: System :: Logging
Requires-Python: >=3.8
License-File: LICENSE
